{
  "tasks": [
    {
      "id": "24",
      "content": "Mow the lawn.",
      "tagIds": [],
      "lastEdit": 1638825026139
    },
    {
      "id": "25",
      "content": "Do homework.",
      "tagIds": [],
      "lastEdit": 1638820282877
    },
    {
      "id": "32",
      "content": "Watch TV.",
      "tagIds": [
        "67"
      ],
      "lastEdit": 1638821981668
    },
    {
      "id": "38",
      "content": "Test tasks.",
      "tagIds": [
        "65"
      ],
      "lastEdit": 1638825056163
    },
    {
      "id": "71",
      "content": "Date test.",
      "tagIds": [
        "65"
      ],
      "lastEdit": 1638825038204
    },
    {
      "id": "72",
      "content": "Take out the garbage.",
      "tagIds": [
        "66"
      ],
      "lastEdit": 1638825690602
    },
    {
      "id": "82",
      "content": "Task task",
      "tagIds": [],
      "lastEdit": 1638968476642
    },
    {
      "id": "89",
      "content": "Eat dinner.",
      "tagIds": [],
      "lastEdit": 1638969540217
    }
  ],
  "lists": [
    {
      "id": "5",
      "title": "To-do",
      "taskIds": [
        "38",
        "71",
        "32",
        "82"
      ]
    },
    {
      "id": "6",
      "title": "Archive",
      "taskIds": [
        "72",
        "89"
      ]
    },
    {
      "id": "89",
      "title": "Test List",
      "taskIds": [
        "24"
      ]
    },
    {
      "id": "90",
      "title": "another",
      "taskIds": []
    },
    {
      "id": "91",
      "title": "Final?",
      "taskIds": []
    }
  ],
  "listOrder": {
    "order": [
      "5",
      "6",
      "89",
      "90",
      "91"
    ]
  },
  "tags": [
    {
      "id": "65",
      "name": "Test"
    },
    {
      "id": "66",
      "name": "Another"
    },
    {
      "id": "67",
      "name": "Urgent!!!"
    }
  ],
  "autoIncrement": {
    "next": 92
  }
}